scraper2_hj3415/__init__.py
scraper2_hj3415/cli.py
scraper2_hj3415/app/__init__.py
scraper2_hj3415/app/composition.py
scraper2_hj3415/app/adapters/__init__.py
scraper2_hj3415/app/adapters/out/__init__.py
scraper2_hj3415/app/adapters/out/playwright/__init__.py
scraper2_hj3415/app/adapters/out/playwright/browser.py
scraper2_hj3415/app/adapters/out/playwright/browser_factory.py
scraper2_hj3415/app/adapters/out/playwright/session.py
scraper2_hj3415/app/adapters/out/sinks/__init__.py
scraper2_hj3415/app/adapters/out/sinks/memory_sink.py
scraper2_hj3415/app/adapters/out/sinks/mongo_sink.py
scraper2_hj3415/app/adapters/out/sinks/store.py
scraper2_hj3415/app/adapters/site/__init__.py
scraper2_hj3415/app/adapters/site/wisereport_playwright.py
scraper2_hj3415/app/domain/__init__.py
scraper2_hj3415/app/domain/blocks.py
scraper2_hj3415/app/domain/constants.py
scraper2_hj3415/app/domain/doc.py
scraper2_hj3415/app/domain/endpoint.py
scraper2_hj3415/app/domain/series.py
scraper2_hj3415/app/domain/types.py
scraper2_hj3415/app/parsing/__init__.py
scraper2_hj3415/app/parsing/c101_parser.py
scraper2_hj3415/app/parsing/c103_parser.py
scraper2_hj3415/app/parsing/c104_parser.py
scraper2_hj3415/app/parsing/c106_parser.py
scraper2_hj3415/app/parsing/c108_parser.py
scraper2_hj3415/app/parsing/_normalize/__init__.py
scraper2_hj3415/app/parsing/_normalize/label.py
scraper2_hj3415/app/parsing/_normalize/table.py
scraper2_hj3415/app/parsing/_normalize/text.py
scraper2_hj3415/app/parsing/_normalize/values.py
scraper2_hj3415/app/parsing/_tables/__init__.py
scraper2_hj3415/app/parsing/_tables/html_table.py
scraper2_hj3415/app/parsing/c101/__init__.py
scraper2_hj3415/app/parsing/c101/_sise_normalizer.py
scraper2_hj3415/app/parsing/c101/company_overview.py
scraper2_hj3415/app/parsing/c101/earning_surprise.py
scraper2_hj3415/app/parsing/c101/fundamentals.py
scraper2_hj3415/app/parsing/c101/major_shareholders.py
scraper2_hj3415/app/parsing/c101/sise.py
scraper2_hj3415/app/parsing/c101/summary_cmp.py
scraper2_hj3415-2.6.0.dist-info/entry_points.txt
scraper2_hj3415-2.6.0.dist-info/licenses/LICENSE
scraper2_hj3415-2.6.0.dist-info/WHEEL
scraper2_hj3415-2.6.0.dist-info/METADATA
scraper2_hj3415-2.6.0.dist-info/RECORD
