Metadata-Version: 2.4
Name: scraper2-hj3415
Version: 2.6.0
Summary: Naver WiseReport scraper
Keywords: example,demo
Author-email: Hyungjin Kim <hj3415@gmail.com>
Requires-Python: >=3.11
Classifier: Programming Language :: Python :: 3
Classifier: License :: OSI Approved :: MIT License
Classifier: Typing :: Typed
License-File: LICENSE
Requires-Dist: playwright>=1.55
Requires-Dist: pandas>=2.3.3
Requires-Dist: pandas-stubs>=2.3.3
Requires-Dist: lxml>=6.0.2
Requires-Dist: typer>=0.21.0
Requires-Dist: db2-hj3415
Requires-Dist: contracts-hj3415
Requires-Dist: common-hj3415
Requires-Dist: logging-hj3415
